Workbook

Sheet excel-заявки в 1 экз. + даты
A1: ОКУД формы | B1: ЦСОД/ СТАТЭК | C1: Полное ведение (ПВ) / Курирование | D1: Краткое наименование | E1: Отчетный период - за | F1: Дата получения каталога со статусом "Итоговый" в АС ГС ОФСН | G1: Дата перевода каталога в "Архивный" статус | H1: код отчётного периода | I1: ОКУД+Код (формула) | J1: Отчетная дата (по бланку) | K1: Период загрузки отчетов (от) | L1: Период загрузки отчетов (до) | M1: Рассылка 1 (дата) | N1: Рассылка 2 (от) | O1: Рассылка 2 (до) | P1: Специалист отраслевого отдела № телефона, кабинет | Q1: Администратор БД от ОИРиТ № телефона, кабинет | R1: Примечание
A2: 0601009 | B2: Ц | C2: ПВ | D2: 1-предприятие | E2: 2024 | F2: =VLOOKUP(I2,'Трансп. каталог'!$F$3:$I$743,2,0) -> 28.12.2024 | G2: =VLOOKUP(I2,'Трансп. каталог'!$F$3:$I$743,3,0) -> С 1 марта по 15 апреля 2025 года | H2: 01012024 | I2: =CONCATENATE(A2,H2) -> 060100901012024 | J2: 15.04.2025 | K2: 27.02.2025 | L2: 15.06.2025 | M2: 27.02.2025 | N2: 09.04.2025 | O2: 11.04.2025 | P2: Чулочникова Н.А., т. 527, к. 431 | Q2: Горячева Светлана Сергеевна, т. 303, к. 307 | R2: =VLOOKUP(I2,'Трансп. каталог'!$F$3:$I$743,4,0) -> 0
A3: 0601011 | B3: Ц | C3: ПВ | D3: 2-МП инновация | E3: 2024 | F3: =VLOOKUP(I3,'Трансп. каталог'!$F$3:$I$743,2,0) -> #N/A | G3: =VLOOKUP(I3,'Трансп. каталог'!$F$3:$I$743,3,0) -> #N/A | H3: 01012024 | I3: =CONCATENATE(A3,H3) -> 060101101012024 | J3: 15.04.2025 | K3: 09.04.2025 | L3: 20.05.2025 | M3: 09.04.2025 | N3: 10.04.2025 | O3: 11.04.2025 | Q3: Трушаева Наталья Ивановна, т. 320, к. 307
A4: 0601013 | B4: С | C4: ПВ | D4: №ПМ | E4: 1 квартал 2025 | F4: =VLOOKUP(I4,'Трансп. каталог'!$F$3:$I$743,2,0) -> не позднее 25.03.2025 | G4: =VLOOKUP(I4,'Трансп. каталог'!$F$3:$I$743,3,0) -> 0 | H4: 04012025 | I4: =CONCATENATE(A4,H4) -> 060101304012025 | J4: 29.04.2025 | K4: 01.04.2025 | L4: 16.05.2025 | M4: 01.04.2025 | N4: 23.04.2025 | O4: 25.04.2025 | P4: Полиенко Оксана Ивановна, т. т. 522, к. к. 303 | Q4: Рублёва Наталья Адольфовна, т. 322, к. 307 | R4: выборочная форма
A5: 0601013 | B5: С | C5: ПВ | D5: №ПМ | E5: 2 квартал 2025 | F5: =VLOOKUP(I5,'Трансп. каталог'!$F$3:$I$743,2,0) -> #N/A | G5: =VLOOKUP(I5,'Трансп. каталог'!$F$3:$I$743,3,0) -> #N/A | H5: 04022025 | I5: =CONCATENATE(A5,H5) -> 060101304022025 | J5: 29.07.2025 | K5: 01.07.2025 | L5: 14.08.2025 | M5: 01.07.2025 | N5: 23.07.2025 | O5: 25.07.2025 | P5: Полиенко Оксана Ивановна, т. т. 522, к. к. 303 | Q5: Рублёва Наталья Адольфовна, т. 322, к. 307 | R5: выборочная форма
A6: 0601013 | B6: С | C6: ПВ | D6: №ПМ | E6: 3 квартал 2025 | F6: =VLOOKUP(I6,'Трансп. каталог'!$F$3:$I$743,2,0) -> #N/A | G6: =VLOOKUP(I6,'Трансп. каталог'!$F$3:$I$743,3,0) -> #N/A | H6: 04032025 | I6: =CONCATENATE(A6,H6) -> 060101304032025 | J6: 29.10.2025 | K6: 01.10.2025 | L6: 12.11.2025 | M6: 01.10.2025 | N6: 22.10.2025 | O6: 24.10.2025 | P6: Полиенко Оксана Ивановна, т. т. 522, к. к. 303 | Q6: Рублёва Наталья Адольфовна, т. 322, к. 307 | R6: выборочная форма
A7: 0601013 | B7: С | C7: ПВ | D7: №ПМ | E7: 4 квартал 2025 | F7: =VLOOKUP(I7,'Трансп. каталог'!$F$3:$I$743,2,0) -> #N/A | G7: =VLOOKUP(I7,'Трансп. каталог'!$F$3:$I$743,3,0) -> #N/A | H7: 04042025 | I7: =CONCATENATE(A7,H7) -> 060101304042025 | J7: 29.01.2026 | K7: 01.01.2026 | L7: 13.02.2026 | M7: 01.01.2026 | N7: 26.01.2026 | O7: 28.01.2026 | P7: Полиенко Оксана Ивановна, т. т. 522, к. к. 303 | Q7: Рублёва Наталья Адольфовна, т. 322, к. 307 | R7: выборочная форма
A8: 0601016 | B8: С | C8: ПВ | D8: МП(микро) | E8: 2024 | F8: =VLOOKUP(I8,'Трансп. каталог'!$F$3:$I$743,2,0) -> не позднее 25.12.2024 | G8: =VLOOKUP(I8,'Трансп. каталог'!$F$3:$I$743,3,0) -> с 1-го официального рабочего дня января по 5 февраля | H8: 01012024 | I8: =CONCATENATE(A8,H8) -> 060101601012024 | J8: 05.02.2025 | K8: 09.01.2025 | L8: 03.03.2025 | M8: 45667 | N8: 03.02.2025 | O8: 04.02.2025 | P8: Меньщикова Галина Николаевна, т. 515, к. 302 | Q8: Рублёва Наталья Адольфовна, т. 322, к. 307 | R8: =VLOOKUP(I8,'Трансп. каталог'!$F$3:$I$743,4,0) -> 0
A9: 0601018 | B9: С | C9: ПВ | D9: 1-ИП | E9: 2024 | F9: =VLOOKUP(I9,'Трансп. каталог'!$F$3:$I$743,2,0) -> не позднее 28.12.2024 | G9: =VLOOKUP(I9,'Трансп. каталог'!$F$3:$I$743,3,0) -> с 10 января по 2 марта | H9: 01012024 | I9: =CONCATENATE(A9,H9) -> 060101801012024 | J9: 02.03.2025 | K9: 45667 | L9: 01.04.2025 | M9: 10.01.2025 | N9: 26.02.2025 | O9: 28.02.2025 | P9: Курликовская Надежда Алексеевна, т. т. 511, к. 305 | Q9: Рублёва Наталья Адольфовна, т. 322, к. 307 | R9: =VLOOKUP(I9,'Трансп. каталог'!$F$3:$I$743,4,0) -> 0
A10: 0601022 | B10: Ц | C10: К | D10: Форма № 1-МО | E10: 2024 | F10: =VLOOKUP(I10,'Трансп. каталог'!$F$3:$I$743,2,0) -> не позднее 28.12.2024 | G10: =VLOOKUP(I10,'Трансп. каталог'!$F$3:$I$743,3,0) -> с 20 апреля по 1 июня после отчетного периода | H10: 01012024 | I10: =CONCATENATE(A10,H10) -> 060102201012024 | J10: 02.06.2025 | K10: 07.04.2025 | L10: 31.07.2025 | M10: 07.04.2025 | N10: 28.05.2025 | O10: 30.05.2025 | P10: Волохова Е.А., т. 371-13-00 доб. 254, к. 423 | Q10: Рублёва Наталья Адольфовна, т. 322, к. 307 | R10: =VLOOKUP(I10,'Трансп. каталог'!$F$3:$I$743,4,0) -> 0
A11: 0601023 | B11: Ц | C11: К | D11: Приложение к форме № 1-МО | E11: 2024 | F11: =VLOOKUP(I11,'Трансп. каталог'!$F$3:$I$743,2,0) -> не позднее 28.12.2024 | G11: =VLOOKUP(I11,'Трансп. каталог'!$F$3:$I$743,3,0) -> с 1 апреля по 25 апреля после отчетного периода | H11: 01012024 | I11: =CONCATENATE(A11,H11) -> 060102301012024 | J11: 25.04.2025 | K11: 17.03.2025 | L11: 30.04.2025 | M11: 17.03.2025 | N11: 22.04.2025 | O11: 24.04.2025 | P11: Волохова Е.А., т. 371-13-00 доб. 254, к. 423 | Q11: Рублёва Наталья Адольфовна, т. 322, к. 307 | R11: =VLOOKUP(I11,'Трансп. каталог'!$F$3:$I$743,4,0) -> 0
A12: 0601024 | B12: Ц | C12: ПВ | D12: МП(микро)-натура | E12: 2024 | F12: =VLOOKUP(I12,'Трансп. каталог'!$F$3:$I$743,2,0) -> не позднее 28.12.2024 | G12: =VLOOKUP(I12,'Трансп. каталог'!$F$3:$I$743,3,0) -> с 1-го официального рабочего дня января по 25 января | H12: 01012024 | I12: =CONCATENATE(A12,H12) -> 060102401012024 | J12: 25.01.2025 | K12: 09.01.2025 | L12: 28.02.2025 | M12: 45670 | N12: 22.01.2025 | O12: 24.01.2025 | P12: Жигулева А.А, т. 509, к. 429 | R12: =VLOOKUP(I12,'Трансп. каталог'!$F$3:$I$743,4,0) -> 0
A13: 0602001 | B13: Ц | C13: К | D13: 11 | E13: 2024 | F13: =VLOOKUP(I13,'Трансп. каталог'!$F$3:$I$743,2,0) -> #N/A | G13: =VLOOKUP(I13,'Трансп. каталог'!$F$3:$I$743,3,0) -> #N/A | H13: 01012024 | I13: =CONCATENATE(A13,H13) -> 060200101012024 | J13: 01.04.2025 | K13: 14.02.2025 | L13: 01.04.2025 | M13: 14.02.2025 | N13: 45742 | O13: 45744 | P13: Покало Марина Владимировна, т. 356, к. 301б | Q13: Фаттахова Гульшат Гадынановна, т. 318, к. 307
A14: 0602002 | B14: Ц | C14: К | D14: 11 (краткая) | E14: 2024 | F14: =VLOOKUP(I14,'Трансп. каталог'!$F$3:$I$743,2,0) -> #N/A | G14: =VLOOKUP(I14,'Трансп. каталог'!$F$3:$I$743,3,0) -> #N/A | H14: 01012024 | I14: =CONCATENATE(A14,H14) -> 060200201012024 | J14: 01.04.2025 | K14: 14.02.2025 | L14: 01.04.2025 | M14: 45708 | N14: 45742 | O14: 45744 | P14: Колбина Ольга Викторовна, т. 358, к. 301б | Q14: Фаттахова Гульшат Гадынановна, т. 318, к. 307
A15: 0602003 | B15: Ц | C15: К | D15: 11 (сделка) | E15: 2024 | F15: =VLOOKUP(I15,'Трансп. каталог'!$F$3:$I$743,2,0) -> #N/A | G15: =VLOOKUP(I15,'Трансп. каталог'!$F$3:$I$743,3,0) -> #N/A | H15: 01012024 | I15: =CONCATENATE(A15,H15) -> 060200301012024 | J15: 45839 | K15: 23.05.2025 | L15: 45839 | M15: 23.05.2025 | N15: 45833 | O15: 45835 | P15: Ивлева Елена Викторовна, т. 352, к. 301а | Q15: Фаттахова Гульшат Гадынановна, т. 318, к. 307 | R15: по наличию явления; 2 рассылки
A16: 0602004 | B16: Ц | C16: К | D16: 11- НА | E16: 2024 | F16: =VLOOKUP(I16,'Трансп. каталог'!$F$3:$I$743,2,0) -> #N/A | G16: =VLOOKUP(I16,'Трансп. каталог'!$F$3:$I$743,3,0) -> #N/A | H16: 01012024 | I16: =CONCATENATE(A16,H16) -> 060200401012024 | J16: 30.06.2025 | K16: 23.05.2025 | L16: 30.06.2025 | M16: 23.05.2025 | N16: 25.06.2025 | O16: 27.06.2025 | P16: Колбина Ольга Викторовна, т. 358, к. 301б | Q16: Фаттахова Гульшат Гадынановна, т. 318, к. 307 | R16: по наличию явления; 2 рассылки
A17: 0603023 | B17: Ц | C17: К | D17: 2-соцподдержка | E17: 1 полугодие 2025 | F17: =VLOOKUP(I17,'Трансп. каталог'!$F$3:$I$743,2,0) -> не позднее 27.06.2025 | G17: =VLOOKUP(I17,'Трансп. каталог'!$F$3:$I$743,3,0) -> 0 | H17: 02012025 | I17: =CONCATENATE(A17,H17) -> 060302302012025 | J17: 15.07.2025 | K17: 30.06.2025 | L17: 21.07.2025 | M17: 30.06.2025 | N17: 09.07.2025 | O17: 11.07.2025 | P17: Антонова Надежда Андреевна, т. 2-86/IP 713, к. 504 | R17: =VLOOKUP(I17,'Трансп. каталог'!$F$3:$I$743,4,0) -> 0
A18: 0603023 | B18: Ц | C18: К | D18: 2-соцподдержка | E18: 2 полугодие 2024 | F18: =VLOOKUP(I18,'Трансп. каталог'!$F$3:$I$743,2,0) -> не позднее 30.12.2025 | G18: =VLOOKUP(I18,'Трансп. каталог'!$F$3:$I$743,3,0) -> 0 | H18: 02022025 | I18: =CONCATENATE(A18,H18) -> 060302302022025 | J18: 45698 | K18: 45687 | L18: 45705 | M18: 45687 | N18: 45694 | O18: 45695 | P18: Антонова Надежда Андреевна, т. 2-86/IP 713, к. 504 | R18: =VLOOKUP(I18,'Трансп. каталог'!$F$3:$I$743,4,0) -> 0
A19: 0603023 | B19: Ц | C19: К | D19: 2-соцподдержка | E19: 2 полугодие 2025 | F19: 15.01.2026 | G19: 02.02.2026 | H19: 17.02.2026 | I19: 02.02.2026 | J19: 15.01.2026 | K19: 02.02.2026 | L19: 17.02.2026 | M19: 02.02.2026 | N19: 12.01.2026 | O19: 14.01.2026 | P19: Антонова Надежда Андреевна, т. 2-86/IP 713, к. 504
A20: 0603027 | B20: С | C20: К | D20: 3-соцподдержка | E20: 2024 | F20: =VLOOKUP(I20,'Трансп. каталог'!$F$3:$I$743,2,0) -> не позднее 13.12.2024 | G20: =VLOOKUP(I20,'Трансп. каталог'!$F$3:$I$743,3,0) -> с 1-го рабочего дня января по 10 февраля после отчетного периода | H20: 01012024 | I20: =CONCATENATE(A20,H20) -> 060302701012024 | J20: 10.02.2025 | K20: 02.01.2025 | L20: 14.02.2025 | M20: 02.01.2025 | N20: 05.02.2025 | O20: 07.02.2025 | P20: Антонова Надежда Андреевна, т. 2-86/IP 713, к. 504 | R20: =VLOOKUP(I20,'Трансп. каталог'!$F$3:$I$743,4,0) -> 0
A21: 0604011 | B21: Ц | C21: ПВ | D21: 2-наука | E21: 2024 | F21: =VLOOKUP(I21,'Трансп. каталог'!$F$3:$I$743,2,0) -> #N/A | G21: =VLOOKUP(I21,'Трансп. каталог'!$F$3:$I$743,3,0) -> #N/A | H21: 01012024 | I21: =CONCATENATE(A21,H21) -> 060401101012024 | J21: 11.04.2025 | K21: 02.04.2025 | L21: 23.05.2025 | M21: 02.04.2025 | N21: 08.04.2025 | O21: 10.04.2025 | P21: Семухина Екатерина Григорьевна, т. 418, к. 301 | Q21: Трушаева Наталья Ивановна, т. 320, к. 307
A22: 0604012 | B22: Ц | C22: К | D22: 2-наука (краткая) | E22: 1 квартал 2025 | F22: =VLOOKUP(I22,'Трансп. каталог'!$F$3:$I$743,2,0) -> не позднее 28.03.2025 | G22: =VLOOKUP(I22,'Трансп. каталог'!$F$3:$I$743,3,0) -> 0 | H22: 04012025 | I22: =CONCATENATE(A22,H22) -> 060401204012025 | J22: 21.04.2025 | K22: 01.04.2025 | L22: 16.05.2025 | M22: 01.04.2025 | N22: 16.04.2025 | O22: 18.04.2025 | P22: Семухина Екатерина Григорьевна, т. 418, к. 302 | Q22: Трушаева Наталья Ивановна, т. 320, к. 307 | R22: =VLOOKUP(I22,'Трансп. каталог'!$F$3:$I$743,4,0) -> 0
A23: 0604012 | B23: Ц | C23: К | D23: 2-наука (краткая) | E23: 2 квартал 2025 | F23: =VLOOKUP(I23,'Трансп. каталог'!$F$3:$I$743,2,0) -> не позднее 01.07.2025 | G23: =VLOOKUP(I23,'Трансп. каталог'!$F$3:$I$743,3,0) -> 0 | H23: 04022025 | I23: =CONCATENATE(A23,H23) -> 060401204022025 | J23: 21.07.2025 | K23: 01.07.2025 | L23: 14.08.2025 | M23: 01.07.2025 | N23: 16.07.2025 | O23: 18.07.2025 | P23: Семухина Екатерина Григорьевна, т. 418, к. 303 | Q23: Трушаева Наталья Ивановна, т. 320, к. 307 | R23: =VLOOKUP(I23,'Трансп. каталог'!$F$3:$I$743,4,0) -> 0
A24: 0604012 | B24: Ц | C24: К | D24: 2-наука (краткая) | E24: 3 квартал 2025 | F24: =VLOOKUP(I24,'Трансп. каталог'!$F$3:$I$743,2,0) -> не позднее 26.09.2025 | G24: =VLOOKUP(I24,'Трансп. каталог'!$F$3:$I$743,3,0) -> 0 | H24: 04032025 | I24: =CONCATENATE(A24,H24) -> 060401204032025 | J24: 20.10.2025 | K24: 01.10.2025 | L24: 14.11.2025 | M24: 01.10.2025 | N24: 15.10.2025 | O24: 17.10.2025 | P24: Семухина Екатерина Григорьевна, т. 418, к. 304 | Q24: Трушаева Наталья Ивановна, т. 320, к. 307 | R24: =VLOOKUP(I24,'Трансп. каталог'!$F$3:$I$743,4,0) -> 0
A25: 0604012 | B25: Ц | C25: К | D25: 2-наука (краткая) | E25: 4 квартал 2025 | F25: =VLOOKUP(I25,'Трансп. каталог'!$F$3:$I$743,2,0) -> не позднее 26.12.2025 | G25: =VLOOKUP(I25,'Трансп. каталог'!$F$3:$I$743,3,0) -> 0 | H25: 04042025 | I25: =CONCATENATE(A25,H25) -> 060401204042025 | J25: 20.01.2026 | K25: 01.01.2026 | L25: 13.02.2026 | M25: 01.01.2026 | N25: 17.01.2026 | O25: 19.01.2026 | P25: Семухина Екатерина Григорьевна, т. 418, к. 305 | Q25: Трушаева Наталья Ивановна, т. 320, к. 307 | R25: =VLOOKUP(I25,'Трансп. каталог'!$F$3:$I$743,4,0) -> 0
A26: 0604016 | B26: Ц | C26: К | D26: 1-Технология | E26: 2024 год | F26: =VLOOKUP(I26,'Трансп. каталог'!$F$3:$I$743,2,0) -> не позднее 27.12.2024 | G26: =VLOOKUP(I26,'Трансп. каталог'!$F$3:$I$743,3,0) -> с 13 января по 31 января после отчетного периода | H26: 01012024 | I26: =CONCATENATE(A26,H26) -> 060401601012024 | J26: 31.01.2025 | K26: 11.01.2025 | L26: 06.03.2025 | M26: 45667 | N26: 28.01.2025 | O26: 30.01.2025 | P26: Ефремова Ирина Анатольевна, т. 408, 2-18, к. 513 | Q26: Трушаева Наталья Ивановна, т. 320, к. 307 | R26: =VLOOKUP(I26,'Трансп. каталог'!$F$3:$I$743,4,0) -> 0
A27: 0604017 | B27: Ц | C27: ПВ | D27: № 4-инновация | E27: 2024 | F27: =VLOOKUP(I27,'Трансп. каталог'!$F$3:$I$743,2,0) -> #N/A | G27: =VLOOKUP(I27,'Трансп. каталог'!$F$3:$I$743,3,0) -> #N/A | H27: 01012024 | I27: =CONCATENATE(A27,H27) -> 060401701012024 | J27: 15.04.2025 | K27: 01.04.2025 | L27: 26.05.2025 | M27: 01.04.2025 | N27: 09.04.2025 | O27: 11.04.2025 | P27: Смагина Татьяна Игоревна, т. 3-40, к. 301 | Q27: Трушаева Наталья Ивановна, т. 320, к. 307
A28: 0604018 | B28: Ц | C28: ПВ | D28: 3-информ | E28: 2024 | F28: =VLOOKUP(I28,'Трансп. каталог'!$F$3:$I$743,2,0) -> #N/A | G28: =VLOOKUP(I28,'Трансп. каталог'!$F$3:$I$743,3,0) -> #N/A | H28: 01012024 | I28: =CONCATENATE(A28,H28) -> 060401801012024 | J28: 45748 | K28: 17.03.2025 | L28: 21.05.2025 | M28: 17.03.2025 | N28: 45742 | O28: 45744 | P28: Панова Ксения Викторовна, т. 371-04-60 (доб. 416), 2-55, к. к. 301 | Q28: Пузакова Марина Владимировна, т. 315, к. 307
A29: 0604023 | B29: Ц | C29: К | D29: 2-МП наука | E29: 2024 | F29: =VLOOKUP(I29,'Трансп. каталог'!$F$3:$I$743,2,0) -> #N/A | G29: =VLOOKUP(I29,'Трансп. каталог'!$F$3:$I$743,3,0) -> #N/A | H29: 01012024 | I29: =CONCATENATE(A29,H29) -> 060402301012024 | J29: 26.05.2025 | K29: 45754 | L29: 23.05.2025 | M29: 14.05.2025 | N29: 21.05.2025 | O29: 23.05.2025 | P29: Крутяева Татьяна Владимировна, т. 401, к. 512 | Q29: Трушаева Наталья Ивановна, т. 320, к. 307
A30: 0604024 | B30: Ц | C30: ПВ | D30: 3-информ (МП) | E30: 2024 | F30: =VLOOKUP(I30,'Трансп. каталог'!$F$3:$I$743,2,0) -> #N/A | G30: =VLOOKUP(I30,'Трансп. каталог'!$F$3:$I$743,3,0) -> #N/A | H30: 01012024 | I30: =CONCATENATE(A30,H30) -> 060402401012024 | J30: 30.04.2025 | K30: 21.04.2025 | L30: 19.06.2025 | M30: 21.04.2025 | N30: 28.04.2025 | O30: 29.04.2025 | P30: Крутяева Татьяна Владимировна, т. 401, к. 512 | Q30: Пузакова Марина Владимировна, т. 315, к. 307
A31: 0604030 | B31: Ц | C31: К | D31: 1-НК | E31: 2024 | F31: =VLOOKUP(I31,'Трансп. каталог'!$F$3:$I$743,2,0) -> не позднее 24.12.2024 | G31: =VLOOKUP(I31,'Трансп. каталог'!$F$3:$I$743,3,0) -> C 9 по 19 января после отчетного периода | H31: 01012024 | I31: =CONCATENATE(A31,H31) -> 060403001012024 | J31: 20.01.2025 | K31: 28.12.2024 | L31: 18.02.2025 | M31: 28.12.2024 | N31: 15.01.2025 | O31: 17.01.2025 | P31: Ожгибцева Юлия Анатольевна, т. 409, к. 513 | Q31: Трушаева Наталья Ивановна, т. 320, к. 307 | R31: =VLOOKUP(I31,'Трансп. каталог'!$F$3:$I$743,4,0) -> 0
A32: 0604041 | B32: Ц | C32: ПВ | D32: 1-робототехника | E32: 2024 | F32: =VLOOKUP(I32,'Трансп. каталог'!$F$3:$I$743,2,0) -> не позднее 26.12.2024 | G32: =VLOOKUP(I32,'Трансп. каталог'!$F$3:$I$743,3,0) -> с 13 по 20 января после отчетного периода | H32: 01012024 | I32: =CONCATENATE(A32,H32) -> 060404101012024 | J32: 20.01.2025 | K32: 09.01.2025 | L32: 05.03.2025 | M32: 09.01.2025 | N32: 15.01.2025 | O32: 17.01.2025 | P32: Порошина Дарья Алексеевна, т. 406, к. 513 | R32: =VLOOKUP(I32,'Трансп. каталог'!$F$3:$I$743,4,0) -> 0
A33: 0606002 | B33: Ц | C33: ПВ | D33: 1-Т | E33: 2024 | F33: =VLOOKUP(I33,'Трансп. каталог'!$F$3:$I$743,2,0) -> не позднее 28.12.2024 | G33: =VLOOKUP(I33,'Трансп. каталог'!$F$3:$I$743,3,0) -> с 1-го рабочего дня по 31 января после отчетного периода | H33: 01012024 | I33: =CONCATENATE(A33,H33) -> 060600201012024 | J33: 31.01.2025 | K33: 28.12.2024 | L33: 21.03.2025 | M33: 28.12.2024 | N33: 28.01.2025 | O33: 30.01.2025 | P33: Велижанина Наталья Владимировна, т. 371-04-60 д. 410, к. 304 | Q33: Горячева Светлана Сергеевна, т. 303, к. 307 | R33: =VLOOKUP(I33,'Трансп. каталог'!$F$3:$I$743,4,0) -> 0
A34: 0606004 | B34: Ц | C34: ПВ | D34: 1-Т (условия труда) | E34: 2024 | F34: =VLOOKUP(I34,'Трансп. каталог'!$F$3:$I$743,2,0) -> не позднее 23.12.2024 | G34: =VLOOKUP(I34,'Трансп. каталог'!$F$3:$I$743,3,0) -> с 1-го рабочего дня по 21 января после отчетного периода | H34: 01012024 | I34: =CONCATENATE(A34,H34) -> 060600401012024 | J34: 21.01.2025 | K34: 28.12.2024 | L34: 28.02.2025 | M34: 28.12.2024 | N34: 15.01.2025 | O34: 17.01.2025 | P34: Миронова Мария Львовна, т. 371-04-60 (426), 3-38, к. к.301 | Q34: Пузакова Марина Владимировна, т. 315, к. 307 | R34: =VLOOKUP(I34,'Трансп. каталог'!$F$3:$I$743,4,0) -> 0
A35: 0606009 | B35: Ц | C35: ПВ | D35: 1-ПР | E35: январь 2025 | F35: =VLOOKUP(I35,'Трансп. каталог'!$F$3:$I$743,2,0) -> не позднее 29.01.2025 | G35: =VLOOKUP(I35,'Трансп. каталог'!$F$3:$I$743,3,0) -> 0 | H35: 12012025 | I35: =CONCATENATE(A35,H35) -> 060600912012025 | J35: 04.02.2025 | K35: 03.02.2025 | L35: 04.02.2025 | M35: - | N35: - | O35: - | P35: Дёмина О.Л., т. 414, к. 301 | Q35: Пузакова Марина Владимировна, т. 315, к. 307 | R35: по наличию явления; нет рассылок
A36: 0606009 | B36: Ц | C36: ПВ | D36: 1-ПР | E36: февраль 2025 | F36: =VLOOKUP(I36,'Трансп. каталог'!$F$3:$I$743,2,0) -> не позднее 26.02.2025 | G36: =VLOOKUP(I36,'Трансп. каталог'!$F$3:$I$743,3,0) -> 0 | H36: 12022025 | I36: =CONCATENATE(A36,H36) -> 060600912022025 | J36: 04.03.2025 | K36: 03.03.2025 | L36: 04.03.2025 | M36: - | N36: - | O36: - | P36: Дёмина О.Л., т. 414, к. 301 | Q36: Пузакова Марина Владимировна, т. 315, к. 307 | R36: по наличию явления; нет рассылок
A37: 0606009 | B37: Ц | C37: ПВ | D37: 1-ПР | E37: март 2025 | F37: =VLOOKUP(I37,'Трансп. каталог'!$F$3:$I$743,2,0) -> не позднее 27.03.2025 | G37: =VLOOKUP(I37,'Трансп. каталог'!$F$3:$I$743,3,0) -> 0 | H37: 12032025 | I37: =CONCATENATE(A37,H37) -> 060600912032025 | J37: 02.04.2025 | K37: 01.04.2025 | L37: 02.04.2025 | M37: - | N37: - | O37: - | P37: Дёмина О.Л., т. 414, к. 301 | Q37: Пузакова Марина Владимировна, т. 315, к. 307 | R37: по наличию явления; нет рассылок
A38: 0606009 | B38: Ц | C38: ПВ | D38: 1-ПР | E38: апрель 2025 | F38: =VLOOKUP(I38,'Трансп. каталог'!$F$3:$I$743,2,0) -> не позднее 25.04.2025 | G38: =VLOOKUP(I38,'Трансп. каталог'!$F$3:$I$743,3,0) -> 0 | H38: 12042025 | I38: =CONCATENATE(A38,H38) -> 060600912042025 | J38: 06.05.2025 | K38: 05.05.2025 | L38: 06.05.2025 | M38: - | N38: - | O38: - | P38: Дёмина О.Л., т. 414, к. 301 | Q38: Пузакова Марина Владимировна, т. 315, к. 307 | R38: по наличию явления; нет рассылок
A39: 0606009 | B39: Ц | C39: ПВ | D39: 1-ПР | E39: май 2025 | F39: =VLOOKUP(I39,'Трансп. каталог'!$F$3:$I$743,2,0) -> не позднее 28.05.2025 | G39: =VLOOKUP(I39,'Трансп. каталог'!$F$3:$I$743,3,0) -> 0 | H39: 12052025 | I39: =CONCATENATE(A39,H39) -> 060600912052025 | J39: 03.06.2025 | K39: 02.06.2025 | L39: 03.06.2025 | M39: - | N39: - | O39: - | P39: Дёмина О.Л., т. 414, к. 301 | Q39: Пузакова Марина Владимировна, т. 315, к. 307 | R39: по наличию явления; нет рассылок
A40: 0606009 | B40: Ц | C40: ПВ | D40: 1-ПР | E40: июнь 2025 | F40: =VLOOKUP(I40,'Трансп. каталог'!$F$3:$I$743,2,0) -> не позднее 26.06.2025 | G40: =VLOOKUP(I40,'Трансп. каталог'!$F$3:$I$743,3,0) -> 0 | H40: 12062025 | I40: =CONCATENATE(A40,H40) -> 060600912062025 | J40: 02.07.2025 | K40: 01.07.2025 | L40: 02.07.2025 | M40: - | N40: - | O40: - | P40: Дёмина О.Л., т. 414, к. 301 | Q40: Пузакова Марина Владимировна, т. 315, к. 307 | R40: по наличию явления; нет рассылок
A41: 0606009 | B41: Ц | C41: ПВ | D41: 1-ПР | E41: июль 2025 | F41: =VLOOKUP(I41,'Трансп. каталог'!$F$3:$I$743,2,0) -> не позднее 29.07.2025 | G41: =VLOOKUP(I41,'Трансп. каталог'!$F$3:$I$743,3,0) -> 0 | H41: 12072025 | I41: =CONCATENATE(A41,H41) -> 060600912072025 | J41: 04.08.2025 | K41: 01.08.2025 | L41: 04.08.2025 | M41: - | N41: - | O41: - | P41: Дёмина О.Л., т. 414, к. 301 | Q41: Пузакова Марина Владимировна, т. 315, к. 307 | R41: по наличию явления; нет рассылок
A42: 0606009 | B42: Ц | C42: ПВ | D42: 1-ПР | E42: август 2025 | F42: =VLOOKUP(I42,'Трансп. каталог'!$F$3:$I$743,2,0) -> не позднее 27.08.2025 | G42: =VLOOKUP(I42,'Трансп. каталог'!$F$3:$I$743,3,0) -> 0 | H42: 12082025 | I42: =CONCATENATE(A42,H42) -> 060600912082025 | J42: 02.09.2025 | K42: 01.09.2025 | L42: 02.09.2025 | M42: - | N42: - | O42: - | P42: Дёмина О.Л., т. 414, к. 301 | Q42: Пузакова Марина Владимировна, т. 315, к. 307 | R42: по наличию явления; нет рассылок
A43: 0606009 | B43: Ц | C43: ПВ | D43: 1-ПР | E43: сентябрь 2025 | F43: =VLOOKUP(I43,'Трансп. каталог'!$F$3:$I$743,2,0) -> не позднее 26.09.2025 | G43: =VLOOKUP(I43,'Трансп. каталог'!$F$3:$I$743,3,0) -> 0 | H43: 12092025 | I43: =CONCATENATE(A43,H43) -> 060600912092025 | J43: 02.10.2025 | K43: 01.10.2025 | L43: 02.10.2025 | M43: - | N43: - | O43: - | P43: Дёмина О.Л., т. 414, к. 301 | Q43: Пузакова Марина Владимировна, т. 315, к. 307 | R43: по наличию явления; нет рассылок
A44: 0606009 | B44: Ц | C44: ПВ | D44: 1-ПР | E44: октябрь 2025 | F44: =VLOOKUP(I44,'Трансп. каталог'!$F$3:$I$743,2,0) -> не позднее 28.10.2025 | G44: =VLOOKUP(I44,'Трансп. каталог'!$F$3:$I$743,3,0) -> 0 | H44: 12102025 | I44: =CONCATENATE(A44,H44) -> 060600912102025 | J44: 05.11.2025 | K44: 01.11.2025 | L44: 05.11.2025 | M44: - | N44: - | O44: - | P44: Дёмина О.Л., т. 414, к. 301 | Q44: Пузакова Марина Владимировна, т. 315, к. 307 | R44: по наличию явления; нет рассылок
A45: 0606009 | B45: Ц | C45: ПВ | D45: 1-ПР | E45: ноябрь 2025 | F45: =VLOOKUP(I45,'Трансп. каталог'!$F$3:$I$743,2,0) -> не позднее 26.11.2025 | G45: =VLOOKUP(I45,'Трансп. каталог'!$F$3:$I$743,3,0) -> 0 | H45: 12112025 | I45: =CONCATENATE(A45,H45) -> 060600912112025 | J45: 02.12.2025 | K45: 01.12.2025 | L45: 02.12.2025 | M45: - | N45: - | O45: - | P45: Дёмина О.Л., т. 414, к. 301 | Q45: Пузакова Марина Владимировна, т. 315, к. 307 | R45: по наличию явления; нет рассылок
A46: 0606009 | B46: Ц | C46: ПВ | D46: 1-ПР | E46: декабрь 2025 | F46: =VLOOKUP(I46,'Трансп. каталог'!$F$3:$I$743,2,0) -> не позднее 26.12.2025 | G46: =VLOOKUP(I46,'Трансп. каталог'!$F$3:$I$743,3,0) -> 0 | H46: 12122025 | I46: =CONCATENATE(A46,H46) -> 060600912122025 | J46: 12.01.2026 | K46: 09.01.2026 | L46: 12.01.2026 | M46: - | N46: - | O46: - | P46: Дёмина О.Л., т. 414, к. 301 | Q46: Пузакова Марина Владимировна, т. 315, к. 307 | R46: по наличию явления; нет рассылок
A47: 0606010 | B47: Ц | C47: ПВ | D47: П-4 | E47: январь 2025 | F47: =VLOOKUP(I47,'Трансп. каталог'!$F$3:$I$743,2,0) -> не позднее 29.01.2025 | G47: =VLOOKUP(I47,'Трансп. каталог'!$F$3:$I$743,3,0) -> 0 | H47: 12012025 | I47: =CONCATENATE(A47,H47) -> 060601012012025 | J47: 17.02.2025 | K47: 01.02.2025 | L47: 25.02.2025 | M47: 01.02.2025 | N47: 12.02.2025 | O47: 14.02.2025 | P47: Дьяконова Светлана Аркадьевна, т. 417, к. 301 | Q47: Горячева Светлана Сергеевна, т. 303, к. 307 | R47: =VLOOKUP(I47,'Трансп. каталог'!$F$3:$I$743,4,0) -> 0
A48: 0606010 | B48: Ц | C48: ПВ | D48: П-4 | E48: февраль 2025 | F48: =VLOOKUP(I48,'Трансп. каталог'!$F$3:$I$743,2,0) -> не позднее 27.02.2025 | G48: =VLOOKUP(I48,'Трансп. каталог'!$F$3:$I$743,3,0) -> 0 | H48: 12022025 | I48: =CONCATENATE(A48,H48) -> 060601012022025 | J48: 17.03.2025 | K48: 01.03.2025 | L48: 25.03.2025 | M48: 01.03.2025 | N48: 12.03.2025 | O48: 14.03.2025 | P48: Дьяконова Светлана Аркадьевна, т. 417, к. 301 | Q48: Горячева Светлана Сергеевна, т. 303, к. 307 | R48: =VLOOKUP(I48,'Трансп. каталог'!$F$3:$I$743,4,0) -> 0
A49: 0606010 | B49: Ц | C49: ПВ | D49: П-4 | E49: март 2025 | F49: =VLOOKUP(I49,'Трансп. каталог'!$F$3:$I$743,2,0) -> не позднее 28.03.2025 | G49: =VLOOKUP(I49,'Трансп. каталог'!$F$3:$I$743,3,0) -> 0 | H49: 12032025 | I49: =CONCATENATE(A49,H49) -> 060601012032025 | J49: 15.04.2025 | K49: 01.04.2025 | L49: 25.04.2025 | M49: 01.04.2025 | N49: 09.04.2025 | O49: 11.04.2025 | P49: Дьяконова Светлана Аркадьевна, т. 417, к. 301 | Q49: Горячева Светлана Сергеевна, т. 303, к. 307 | R49: =VLOOKUP(I49,'Трансп. каталог'!$F$3:$I$743,4,0) -> 0
A50: 0606010 | B50: Ц | C50: ПВ | D50: П-4 | E50: апрель 2025 | F50: =VLOOKUP(I50,'Трансп. каталог'!$F$3:$I$743,2,0) -> не позднее 28.04.2025 | G50: =VLOOKUP(I50,'Трансп. каталог'!$F$3:$I$743,3,0) -> 0 | H50: 12042025 | I50: =CONCATENATE(A50,H50) -> 060601012042025 | J50: 15.05.2025 | K50: 01.05.2025 | L50: 26.05.2025 | M50: 01.05.2025 | N50: 12.05.2025 | O50: 14.05.2025 | P50: Дьяконова Светлана Аркадьевна, т. 417, к. 301 | Q50: Горячева Светлана Сергеевна, т. 303, к. 307 | R50: =VLOOKUP(I50,'Трансп. каталог'!$F$3:$I$743,4,0) -> 0
A51: 0606010 | B51: Ц | C51: ПВ | D51: П-4 | E51: май 2025 | F51: =VLOOKUP(I51,'Трансп. каталог'!$F$3:$I$743,2,0) -> не позднее 29.05.2025 | G51: =VLOOKUP(I51,'Трансп. каталог'!$F$3:$I$743,3,0) -> 0 | H51: 12052025 | I51: =CONCATENATE(A51,H51) -> 060601012052025 | J51: 16.06.2025 | K51: 01.06.2025 | L51: 25.06.2025 | M51: 45810 | N51: 09.06.2025 | O51: 11.06.2025 | P51: Дьяконова Светлана Аркадьевна, т. 417, к. 301 | Q51: Горячева Светлана Сергеевна, т. 303, к. 307 | R51: =VLOOKUP(I51,'Трансп. каталог'!$F$3:$I$743,4,0) -> 0
A52: 0606010 | B52: Ц | C52: ПВ | D52: П-4 | E52: июнь 2025 | F52: =VLOOKUP(I52,'Трансп. каталог'!$F$3:$I$743,2,0) -> не позднее 27.06.2025 | G52: =VLOOKUP(I52,'Трансп. каталог'!$F$3:$I$743,3,0) -> 0 | H52: 12062025 | I52: =CONCATENATE(A52,H52) -> 060601012062025 | J52: 15.07.2025 | K52: 01.07.2025 | L52: 25.07.2025 | M52: 01.07.2025 | N52: 09.07.2025 | O52: 11.07.2025 | P52: Дьяконова Светлана Аркадьевна, т. 417, к. 301 | Q52: Горячева Светлана Сергеевна, т. 303, к. 307 | R52: =VLOOKUP(I52,'Трансп. каталог'!$F$3:$I$743,4,0) -> 0
A53: 0606010 | B53: Ц | C53: ПВ | D53: П-4 | E53: июль 2025 | F53: =VLOOKUP(I53,'Трансп. каталог'!$F$3:$I$743,2,0) -> не позднее 29.07.2025 | G53: =VLOOKUP(I53,'Трансп. каталог'!$F$3:$I$743,3,0) -> 0 | H53: 12072025 | I53: =CONCATENATE(A53,H53) -> 060601012072025 | J53: 15.08.2025 | K53: 01.08.2025 | L53: 26.08.2025 | M53: 01.08.2025 | N53: 12.08.2025 | O53: 14.08.2025 | P53: Дьяконова Светлана Аркадьевна, т. 417, к. 301 | Q53: Горячева Светлана Сергеевна, т. 303, к. 307 | R53: =VLOOKUP(I53,'Трансп. каталог'!$F$3:$I$743,4,0) -> 0
A54: 0606010 | B54: Ц | C54: ПВ | D54: П-4 | E54: август 2025 | F54: =VLOOKUP(I54,'Трансп. каталог'!$F$3:$I$743,2,0) -> не позднее 29.08.2025 | G54: =VLOOKUP(I54,'Трансп. каталог'!$F$3:$I$743,3,0) -> 0 | H54: 12082025 | I54: =CONCATENATE(A54,H54) -> 060601012082025 | J54: 15.09.2025 | K54: 01.09.2025 | L54: 25.09.2025 | M54: 01.09.2025 | N54: 10.09.2025 | O54: 12.09.2025 | P54: Дьяконова Светлана Аркадьевна, т. 417, к. 301 | Q54: Горячева Светлана Сергеевна, т. 303, к. 307 | R54: =VLOOKUP(I54,'Трансп. каталог'!$F$3:$I$743,4,0) -> 0
A55: 0606010 | B55: Ц | C55: ПВ | D55: П-4 | E55: сентябрь 2025 | F55: =VLOOKUP(I55,'Трансп. каталог'!$F$3:$I$743,2,0) -> не позднее 26.09.2025 | G55: =VLOOKUP(I55,'Трансп. каталог'!$F$3:$I$743,3,0) -> 0 | H55: 12092025 | I55: =CONCATENATE(A55,H55) -> 060601012092025 | J55: 15.10.2025 | K55: 01.10.2025 | L55: 27.10.2025 | M55: 01.10.2025 | N55: 08.10.2025 | O55: 10.10.2025 | P55: Дьяконова Светлана Аркадьевна, т. 417, к. 301 | Q55: Горячева Светлана Сергеевна, т. 303, к. 307 | R55: =VLOOKUP(I55,'Трансп. каталог'!$F$3:$I$743,4,0) -> 0
A56: 0606010 | B56: Ц | C56: ПВ | D56: П-4 | E56: октябрь 2025 | F56: =VLOOKUP(I56,'Трансп. каталог'!$F$3:$I$743,2,0) -> не позднее 29.10.2025 | G56: =VLOOKUP(I56,'Трансп. каталог'!$F$3:$I$743,3,0) -> 0 | H56: 12102025 | I56: =CONCATENATE(A56,H56) -> 060601012102025 | J56: 17.11.2025 | K56: 01.11.2025 | L56: 26.11.2025 | M56: 01.11.2025 | N56: 12.11.2025 | O56: 14.11.2025 | P56: Дьяконова Светлана Аркадьевна, т. 417, к. 301 | Q56: Горячева Светлана Сергеевна, т. 303, к. 307 | R56: =VLOOKUP(I56,'Трансп. каталог'!$F$3:$I$743,4,0) -> 0
A57: 0606010 | B57: Ц | C57: ПВ | D57: П-4 | E57: ноябрь 2025 | F57: =VLOOKUP(I57,'Трансп. каталог'!$F$3:$I$743,2,0) -> не позднее 28.11.2025 | G57: =VLOOKUP(I57,'Трансп. каталог'!$F$3:$I$743,3,0) -> 0 | H57: 12112025 | I57: =CONCATENATE(A57,H57) -> 060601012112025 | J57: 15.12.2025 | K57: 01.12.2025 | L57: 25.12.2025 | M57: 01.12.2025 | N57: 10.12.2025 | O57: 12.12.2025 | P57: Дьяконова Светлана Аркадьевна, т. 417, к. 301 | Q57: Горячева Светлана Сергеевна, т. 303, к. 307 | R57: =VLOOKUP(I57,'Трансп. каталог'!$F$3:$I$743,4,0) -> 0
A58: 0606010 | B58: Ц | C58: ПВ | D58: П-4 | E58: декабрь 2025 | F58: =VLOOKUP(I58,'Трансп. каталог'!$F$3:$I$743,2,0) -> не позднее 26.12.2025 | G58: =VLOOKUP(I58,'Трансп. каталог'!$F$3:$I$743,3,0) -> 0 | H58: 12122025 | I58: =CONCATENATE(A58,H58) -> 060601012122025 | J58: 15.01.2026 | K58: 01.01.2026 | L58: 26.01.2026 | M58: 01.01.2026 | N58: 12.01.2026 | O58: 14.01.2026 | P58: Дьяконова Светлана Аркадьевна, т. 417, к. 301 | Q58: Горячева Светлана Сергеевна, т. 303, к. 307 | R58: =VLOOKUP(I58,'Трансп. каталог'!$F$3:$I$743,4,0) -> 0
A59: 0606010 | B59: Ц | C59: ПВ | D59: П-4 до 15 | E59: 1 квартал 2025 | F59: =VLOOKUP(I59,'Трансп. каталог'!$F$3:$I$743,2,0) -> не позднее 28.03.2025 | G59: =VLOOKUP(I59,'Трансп. каталог'!$F$3:$I$743,3,0) -> 0 | H59: 04012025 | I59: =CONCATENATE(A59,H59) -> 060601004012025 | J59: 15.04.2025 | K59: 01.04.2025 | L59: 25.04.2025 | M59: 01.04.2025 | N59: 09.04.2025 | O59: 11.04.2025 | P59: Красикова Анастасия Сергеевна, т. 371-04-60(доб.419), к. 510 | Q59: Горячева Светлана Сергеевна, т. 303, к. 307 | R59: =VLOOKUP(I59,'Трансп. каталог'!$F$3:$I$743,4,0) -> 0
A60: 0606010 | B60: Ц | C60: ПВ | D60: П-4 до 15 | E60: 2 квартал 2025 | F60: =VLOOKUP(I60,'Трансп. каталог'!$F$3:$I$743,2,0) -> не позднее 27.06.2025 | G60: =VLOOKUP(I60,'Трансп. каталог'!$F$3:$I$743,3,0) -> 0 | H60: 04022025 | I60: =CONCATENATE(A60,H60) -> 060601004022025 | J60: 15.07.2025 | K60: 01.07.2025 | L60: 25.07.2025 | M60: 01.07.2025 | N60: 09.07.2025 | O60: 11.07.2025 | P60: Красикова Анастасия Сергеевна, т. 371-04-60(доб.419), к. 510 | Q60: Горячева Светлана Сергеевна, т. 303, к. 307 | R60: =VLOOKUP(I60,'Трансп. каталог'!$F$3:$I$743,4,0) -> 0
A61: 0606010 | B61: Ц | C61: ПВ | D61: П-4 до 15 | E61: 3 квартал 2025 | F61: =VLOOKUP(I61,'Трансп. каталог'!$F$3:$I$743,2,0) -> не позднее 26.09.2025 | G61: =VLOOKUP(I61,'Трансп. каталог'!$F$3:$I$743,3,0) -> 0 | H61: 04032025 | I61: =CONCATENATE(A61,H61) -> 060601004032025 | J61: 15.10.2025 | K61: 01.10.2025 | L61: 24.10.2025 | M61: 01.10.2025 | N61: 08.10.2025 | O61: 10.10.2025 | P61: Красикова Анастасия Сергеевна, т. 371-04-60(доб.419), к. 510 | Q61: Горячева Светлана Сергеевна, т. 303, к. 307 | R61: =VLOOKUP(I61,'Трансп. каталог'!$F$3:$I$743,4,0) -> 0
A62: 0606010 | B62: Ц | C62: ПВ | D62: П-4 до 15 | E62: 4 квартал 2025 | F62: =VLOOKUP(I62,'Трансп. каталог'!$F$3:$I$743,2,0) -> не позднее 26.12.2025 | G62: =VLOOKUP(I62,'Трансп. каталог'!$F$3:$I$743,3,0) -> 0 | H62: 04042025 | I62: =CONCATENATE(A62,H62) -> 060601004042025 | J62: 15.01.2026 | K62: 01.01.2026 | L62: 23.01.2026 | M62: 01.01.2026 | N62: 12.01.2026 | O62: 14.01.2026 | P62: Красикова Анастасия Сергеевна, т. 371-04-60(доб.419), к. 510 | Q62: Горячева Светлана Сергеевна, т. 303, к. 307 | R62: =VLOOKUP(I62,'Трансп. каталог'!$F$3:$I$743,4,0) -> 0
A63: 0606013 | B63: Ц | C63: ПВ | D63: 3-Ф | E63: январь 2025 | F63: =VLOOKUP(I63,'Трансп. каталог'!$F$3:$I$743,2,0) -> не позднее 29.01.2025 | G63: =VLOOKUP(I63,'Трансп. каталог'!$F$3:$I$743,3,0) -> 0 | H63: 12012025 | I63: =CONCATENATE(A63,H63) -> 060601312012025 | J63: 04.02.2025 | K63: 31.01.2025 | L63: 04.02.2025 | M63: 31.01.2025 | N63: - | O63: - | P63: Ожгибцева Юлия Анатольевна, т. 2-18,409, к. 513 | Q63: Рублёва Наталья Адольфовна, т. 322, к. 307 | R63: по наличию явления; 1 рассылка
A64: 0606013 | B64: Ц | C64: ПВ | D64: 3-Ф | E64: февраль 2025 | F64: =VLOOKUP(I64,'Трансп. каталог'!$F$3:$I$743,2,0) -> не позднее 27.02.2025 | G64: =VLOOKUP(I64,'Трансп. каталог'!$F$3:$I$743,3,0) -> 0 | H64: 12022025 | I64: =CONCATENATE(A64,H64) -> 060601312022025 | J64: 04.03.2025 | K64: 28.02.2025 | L64: 04.03.2025 | M64: 28.02.2025 | N64: - | O64: - | P64: Ожгибцева Юлия Анатольевна, т. 2-18,409, к. 513 | Q64: Рублёва Наталья Адольфовна, т. 322, к. 307 | R64: по наличию явления; 1 рассылка
A65: 0606013 | B65: Ц | C65: ПВ | D65: 3-Ф | E65: март 2025 | F65: =VLOOKUP(I65,'Трансп. каталог'!$F$3:$I$743,2,0) -> не позднее 28.03.2025 | G65: =VLOOKUP(I65,'Трансп. каталог'!$F$3:$I$743,3,0) -> 0 | H65: 12032025 | I65: =CONCATENATE(A65,H65) -> 060601312032025 | J65: 02.04.2025 | K65: 31.03.2025 | L65: 02.04.2025 | M65: 31.03.2025 | N65: - | O65: - | P65: Ожгибцева Юлия Анатольевна, т. 2-18,409, к. 513 | Q65: Рублёва Наталья Адольфовна, т. 322, к. 307 | R65: по наличию явления; 1 рассылка
A66: 0606013 | B66: Ц | C66: ПВ | D66: 3-Ф | E66: апрель 2025 | F66: =VLOOKUP(I66,'Трансп. каталог'!$F$3:$I$743,2,0) -> не позднее 28.04.2025 | G66: =VLOOKUP(I66,'Трансп. каталог'!$F$3:$I$743,3,0) -> 0 | H66: 12042025 | I66: =CONCATENATE(A66,H66) -> 060601312042025 | J66: 06.05.2025 | K66: 30.04.2025 | L66: 06.05.2025 | M66: 30.04.2025 | N66: - | O66: - | P66: Ожгибцева Юлия Анатольевна, т. 2-18,409, к. 513 | Q66: Рублёва Наталья Адольфовна, т. 322, к. 307 | R66: по наличию явления; 1 рассылка
A67: 0606013 | B67: Ц | C67: ПВ | D67: 3-Ф | E67: май 2025 | F67: =VLOOKUP(I67,'Трансп. каталог'!$F$3:$I$743,2,0) -> не позднее 29.05.2025 | G67: =VLOOKUP(I67,'Трансп. каталог'!$F$3:$I$743,3,0) -> 0 | H67: 12052025 | I67: =CONCATENATE(A67,H67) -> 060601312052025 | J67: 03.06.2025 | K67: 30.05.2025 | L67: 03.06.2025 | M67: 30.05.2025 | N67: - | O67: - | P67: Ожгибцева Юлия Анатольевна, т. 2-18,409, к. 513 | Q67: Рублёва Наталья Адольфовна, т. 322, к. 307 | R67: по наличию явления; 1 рассылка
A68: 0606013 | B68: Ц | C68: ПВ | D68: 3-Ф | E68: июнь 2025 | F68: =VLOOKUP(I68,'Трансп. каталог'!$F$3:$I$743,2,0) -> не позднее 27.06.2025 | G68: =VLOOKUP(I68,'Трансп. каталог'!$F$3:$I$743,3,0) -> 0 | H68: 12062025 | I68: =CONCATENATE(A68,H68) -> 060601312062025 | J68: 02.07.2025 | K68: 30.06.2025 | L68: 02.07.2025 | M68: 30.06.2025 | N68: - | O68: - | P68: Ожгибцева Юлия Анатольевна, т. 2-18,409, к. 513 | Q68: Рублёва Наталья Адольфовна, т. 322, к. 307 | R68: по наличию явления; 1 рассылка
A69: 0606013 | B69: Ц | C69: ПВ | D69: 3-Ф | E69: июль 2025 | F69: =VLOOKUP(I69,'Трансп. каталог'!$F$3:$I$743,2,0) -> не позднее 29.07.2025 | G69: =VLOOKUP(I69,'Трансп. каталог'!$F$3:$I$743,3,0) -> 0 | H69: 12072025 | I69: =CONCATENATE(A69,H69) -> 060601312072025 | J69: 04.08.2025 | K69: 31.07.2025 | L69: 04.08.2025 | M69: 31.07.2025 | N69: - | O69: - | P69: Ожгибцева Юлия Анатольевна, т. 2-18,409, к. 513 | Q69: Рублёва Наталья Адольфовна, т. 322, к. 307 | R69: по наличию явления; 1 рассылка
A70: 0606013 | B70: Ц | C70: ПВ | D70: 3-Ф | E70: август 2025 | F70: =VLOOKUP(I70,'Трансп. каталог'!$F$3:$I$743,2,0) -> не позднее 29.08.2025 | G70: =VLOOKUP(I70,'Трансп. каталог'!$F$3:$I$743,3,0) -> 0 | H70: 12082025 | I70: =CONCATENATE(A70,H70) -> 060601312082025 | J70: 02.09.2025 | K70: 29.08.2025 | L70: 02.09.2025 | M70: 29.08.2025 | N70: - | O70: - | P70: Ожгибцева Юлия Анатольевна, т. 2-18,409, к. 513 | Q70: Рублёва Наталья Адольфовна, т. 322, к. 307 | R70: по наличию явления; 1 рассылка
A71: 0606013 | B71: Ц | C71: ПВ | D71: 3-Ф | E71: сентябрь 2025 | F71: =VLOOKUP(I71,'Трансп. каталог'!$F$3:$I$743,2,0) -> не позднее 26.09.2025 | G71: =VLOOKUP(I71,'Трансп. каталог'!$F$3:$I$743,3,0) -> 0 | H71: 12092025 | I71: =CONCATENATE(A71,H71) -> 060601312092025 | J71: 02.10.2025 | K71: 30.09.2025 | L71: 02.10.2025 | M71: 30.09.2025 | N71: - | O71: - | P71: Ожгибцева Юлия Анатольевна, т. 2-18,409, к. 513 | Q71: Рублёва Наталья Адольфовна, т. 322, к. 307 | R71: по наличию явления; 1 рассылка
A72: 0606013 | B72: Ц | C72: ПВ | D72: 3-Ф | E72: октябрь 2025 | F72: =VLOOKUP(I72,'Трансп. каталог'!$F$3:$I$743,2,0) -> не позднее 29.10.2025 | G72: =VLOOKUP(I72,'Трансп. каталог'!$F$3:$I$743,3,0) -> 0 | H72: 12102025 | I72: =CONCATENATE(A72,H72) -> 060601312102025 | J72: 05.11.2025 | K72: 31.10.2025 | L72: 05.11.2025 | M72: 31.10.2025 | N72: - | O72: - | P72: Ожгибцева Юлия Анатольевна, т. 2-18,409, к. 513 | Q72: Рублёва Наталья Адольфовна, т. 322, к. 307 | R72: по наличию явления; 1 рассылка
A73: 0606013 | B73: Ц | C73: ПВ | D73: 3-Ф | E73: ноябрь 2025 | F73: =VLOOKUP(I73,'Трансп. каталог'!$F$3:$I$743,2,0) -> не позднее 28.11.2025 | G73: =VLOOKUP(I73,'Трансп. каталог'!$F$3:$I$743,3,0) -> 0 | H73: 12112025 | I73: =CONCATENATE(A73,H73) -> 060601312112025 | J73: 02.12.2025 | K73: 28.11.2025 | L73: 02.12.2025 | M73: 28.11.2025 | N73: - | O73: - | P73: Ожгибцева Юлия Анатольевна, т. 2-18,409, к. 513 | Q73: Рублёва Наталья Адольфовна, т. 322, к. 307 | R73: по наличию явления; 1 рассылка
A74: 0606013 | B74: Ц | C74: ПВ | D74: 3-Ф | E74: декабрь 2025 | F74: =VLOOKUP(I74,'Трансп. каталог'!$F$3:$I$743,2,0) -> не позднее 26.12.2025 | G74: =VLOOKUP(I74,'Трансп. каталог'!$F$3:$I$743,3,0) -> 0 | H74: 12122025 | I74: =CONCATENATE(A74,H74) -> 060601312122025 | J74: 09.01.2026 | K74: 30.12.2025 | L74: 12.01.2026 | M74: 30.12.2025 | N74: - | O74: - | P74: Ожгибцева Юлия Анатольевна, т. 2-18,409, к. 513 | Q74: Рублёва Наталья Адольфовна, т. 322, к. 307 | R74: по наличию явления; 1 рассылка
A75: 0606028 | B75: Ц | C75: ПВ | D75: П-4 (НЗ) | E75: 1 квартал 2025 | F75: =VLOOKUP(I75,'Трансп. каталог'!$F$3:$I$743,2,0) -> не позднее 28.03.2025 | G75: =VLOOKUP(I75,'Трансп. каталог'!$F$3:$I$743,3,0) -> 0 | H75: 04012025 | I75: =CONCATENATE(A75,H75) -> 060602804012025 | J75: 08.04.2025 | K75: 29.03.2025 | L75: 17.04.2025 | M75: 45747 | N75: 02.04.2025 | O75: 04.04.2025 | P75: Суркова Е.А., т. 420, к. 304 | Q75: Усова Яна Сергеевна, т. 321, к. 307 | R75: =VLOOKUP(I75,'Трансп. каталог'!$F$3:$I$743,4,0) -> 0
A76: 0606028 | B76: Ц | C76: ПВ | D76: П-4 (НЗ) | E76: 2 квартал 2025 | F76: =VLOOKUP(I76,'Трансп. каталог'!$F$3:$I$743,2,0) -> не позднее 27.06.2025 | G76: =VLOOKUP(I76,'Трансп. каталог'!$F$3:$I$743,3,0) -> 0 | H76: 04022025 | I76: =CONCATENATE(A76,H76) -> 060602804022025 | J76: 08.07.2025 | K76: 28.06.2025 | L76: 17.07.2025 | M76: 28.06.2025 | N76: 02.07.2025 | O76: 04.07.2025 | P76: Суркова Е.А., т. 420, к. 304 | Q76: Усова Яна Сергеевна, т. 321, к. 307 | R76: =VLOOKUP(I76,'Трансп. каталог'!$F$3:$I$743,4,0) -> 0
A77: 0606028 | B77: Ц | C77: ПВ | D77: П-4 (НЗ) | E77: 3 квартал 2025 | F77: =VLOOKUP(I77,'Трансп. каталог'!$F$3:$I$743,2,0) -> не позднее 26.09.2025 | G77: =VLOOKUP(I77,'Трансп. каталог'!$F$3:$I$743,3,0) -> 0 | H77: 04032025 | I77: =CONCATENATE(A77,H77) -> 060602804032025 | J77: 08.10.2025 | K77: 27.09.2025 | L77: 17.10.2025 | M77: 27.09.2025 | N77: 01.10.2025 | O77: 03.10.2025 | P77: Суркова Е.А., т. 420, к. 304 | Q77: Усова Яна Сергеевна, т. 321, к. 307 | R77: =VLOOKUP(I77,'Трансп. каталог'!$F$3:$I$743,4,0) -> 0
A78: 0606028 | B78: Ц | C78: ПВ | D78: П-4 (НЗ) | E78: 4 квартал 2025 | F78: =VLOOKUP(I78,'Трансп. каталог'!$F$3:$I$743,2,0) -> не позднее 26.12.2025 | G78: =VLOOKUP(I78,'Трансп. каталог'!$F$3:$I$743,3,0) -> 0 | H78: 04042025 | I78: =CONCATENATE(A78,H78) -> 060602804042025 | J78: 10.01.2026 | K78: 27.12.2025 | L78: 23.01.2026 | M78: 27.12.2025 | N78: 07.01.2026 | O78: 09.01.2026 | P78: Суркова Е.А., т. 420, к. 304 | Q78: Усова Яна Сергеевна, т. 321, к. 307 | R78: =VLOOKUP(I78,'Трансп. каталог'!$F$3:$I$743,4,0) -> 0
A79: 0606038 | B79: С | C79: ПВ | D79: Форма № 1 | E79: 2025 | F79: =VLOOKUP(I79,'Трансп. каталог'!$F$3:$I$743,2,0) -> не позднее 21.04.2025 | G79: =VLOOKUP(I79,'Трансп. каталог'!$F$3:$I$743,3,0) -> с 1-го рабочего дня по 20 мая после отчетного периода | H79: 01012025 | I79: =CONCATENATE(A79,H79) -> 060603801012025 | J79: 20.05.2026 | K79: 28.04.2025 | L79: 10.06.2025 | M79: 28.04.2025 | N79: 14.05.2026 | O79: 16.05.2026 | P79: Максимова Мария Владимировна 371-04-60 доб. 421, к. 304 | Q79: Трушаева Наталья Ивановна, т. 320, к. 307 | R79: =VLOOKUP(I79,'Трансп. каталог'!$F$3:$I$743,4,0) -> 0
A80: 0606045 | B80: другое ПО | C80: ПВ | D80: Форма № ЗП-здрав | E80: 1 квартал 2025 | F80: =VLOOKUP(I80,'Трансп. каталог'!$F$3:$I$743,2,0) -> не позднее 28.03.2025 | G80: =VLOOKUP(I80,'Трансп. каталог'!$F$3:$I$743,3,0) -> 0 | H80: 04012025 | I80: =CONCATENATE(A80,H80) -> 060604504012025 | J80: 10.04.2025 | K80: 31.03.2025 | L80: 24.04.2025 | M80: 31.03.2025 | N80: 07.04.2025 | O80: 09.04.2025 | Q80: Фаттахова Гульшат Гадынановна, т. 318, к. 307 | R80: по наличию явления; 2 рассылки
A81: 0606045 | B81: другое ПО | C81: ПВ | D81: Форма № ЗП-здрав | E81: 2 квартал 2025 | F81: =VLOOKUP(I81,'Трансп. каталог'!$F$3:$I$743,2,0) -> не позднее 30.06.2025 | G81: =VLOOKUP(I81,'Трансп. каталог'!$F$3:$I$743,3,0) -> 0 | H81: 04022025 | I81: =CONCATENATE(A81,H81) -> 060604504022025 | J81: 10.07.2025 | K81: 30.06.2025 | L81: 24.07.2025 | M81: 30.06.2025 | N81: 07.07.2025 | O81: 09.07.2025 | Q81: Фаттахова Гульшат Гадынановна, т. 318, к. 307 | R81: по наличию явления; 2 рассылки
A82: 0606045 | B82: другое ПО | C82: ПВ | D82: Форма № ЗП-здрав | E82: 3 квартал 2025 | F82: =VLOOKUP(I82,'Трансп. каталог'!$F$3:$I$743,2,0) -> не позднее 29.09.2025 | G82: =VLOOKUP(I82,'Трансп. каталог'!$F$3:$I$743,3,0) -> 0 | H82: 04032025 | I82: =CONCATENATE(A82,H82) -> 060604504032025 | J82: 10.10.2025 | K82: 29.09.2025 | L82: 24.10.2025 | M82: 29.09.2025 | N82: 07.10.2025 | O82: 09.10.2025 | Q82: Фаттахова Гульшат Гадынановна, т. 318, к. 307 | R82: по наличию явления; 2 рассылки
A83: 0606045 | B83: другое ПО | C83: ПВ | D83: Форма № ЗП-здрав | E83: 4 квартал 2025 | F83: =VLOOKUP(I83,'Трансп. каталог'!$F$3:$I$743,2,0) -> не позднее 29.12.2025 | G83: =VLOOKUP(I83,'Трансп. каталог'!$F$3:$I$743,3,0) -> 0 | H83: 04042025 | I83: =CONCATENATE(A83,H83) -> 060604504042025 | J83: 12.01.2026 | K83: 29.12.2025 | L83: 30.01.2026 | M83: 29.12.2025 | N83: 09.01.2026 | O83: 11.01.2026 | Q83: Фаттахова Гульшат Гадынановна, т. 318, к. 307 | R83: по наличию явления; 2 рассылки
A84: 0606046 | B84: другое ПО | C84: ПВ | D84: Форма № ЗП-культура | E84: 1 квартал 2025 | F84: =VLOOKUP(I84,'Трансп. каталог'!$F$3:$I$743,2,0) -> не позднее 28.03.2025 | G84: =VLOOKUP(I84,'Трансп. каталог'!$F$3:$I$743,3,0) -> 0 | H84: 04012025 | I84: =CONCATENATE(A84,H84) -> 060604604012025 | J84: 10.04.2025 | K84: 31.03.2025 | L84: 24.04.2025 | M84: 31.03.2025 | N84: 07.04.2025 | O84: 09.04.2025 | Q84: Фаттахова Гульшат Гадынановна, т. 318, к. 307 | R84: по наличию явления; 2 рассылки
A85: 0606046 | B85: другое ПО | C85: ПВ | D85: Форма № ЗП-культура | E85: 2 квартал 2025 | F85: =VLOOKUP(I85,'Трансп. каталог'!$F$3:$I$743,2,0) -> не позднее 30.06.2025 | G85: =VLOOKUP(I85,'Трансп. каталог'!$F$3:$I$743,3,0) -> 0 | H85: 04022025 | I85: =CONCATENATE(A85,H85) -> 060604604022025 | J85: 10.07.2025 | K85: 30.06.2025 | L85: 24.07.2025 | M85: 30.06.2025 | N85: 07.07.2025 | O85: 09.07.2025 | Q85: Фаттахова Гульшат Гадынановна, т. 318, к. 307 | R85: по наличию явления; 2 рассылки
A86: 0606046 | B86: другое ПО | C86: ПВ | D86: Форма № ЗП-культура | E86: 3 квартал 2025 | F86: =VLOOKUP(I86,'Трансп. каталог'!$F$3:$I$743,2,0) -> не позднее 29.09.2025 | G86: =VLOOKUP(I86,'Трансп. каталог'!$F$3:$I$743,3,0) -> 0 | H86: 04032025 | I86: =CONCATENATE(A86,H86) -> 060604604032025 | J86: 10.10.2025 | K86: 29.09.2025 | L86: 24.10.2025 | M86: 29.09.2025 | N86: 07.10.2025 | O86: 09.10.2025 | Q86: Фаттахова Гульшат Гадынановна, т. 318, к. 307 | R86: по наличию явления; 2 рассылки
A87: 0606046 | B87: другое ПО | C87: ПВ | D87: Форма № ЗП-культура | E87: 4 квартал 2025 | F87: =VLOOKUP(I87,'Трансп. каталог'!$F$3:$I$743,2,0) -> не позднее 29.12.2025 | G87: =VLOOKUP(I87,'Трансп. каталог'!$F$3:$I$743,3,0) -> 0 | H87: 04042025 | I87: =CONCATENATE(A87,H87) -> 060604604042025 | J87: 12.01.2026 | K87: 29.12.2025 | L87: 30.01.2026 | M87: 29.12.2025 | N87: 09.01.2026 | O87: 11.01.2026 | Q87: Фаттахова Гульшат Гадынановна, т. 318, к. 307 | R87: по наличию явления; 2 рассылки
A88: 0606047 | B88: другое ПО | C88: ПВ | D88: Форма № 3П-наука | E88: 1 квартал 2025 | F88: =VLOOKUP(I88,'Трансп. каталог'!$F$3:$I$743,2,0) -> не позднее 28.03.2025 | G88: =VLOOKUP(I88,'Трансп. каталог'!$F$3:$I$743,3,0) -> 0 | H88: 04012025 | I88: =CONCATENATE(A88,H88) -> 060604704012025 | J88: 10.04.2025 | K88: 31.03.2025 | L88: 24.04.2025 | M88: 31.03.2025 | N88: 07.04.2025 | O88: 09.04.2025 | Q88: Фаттахова Гульшат Гадынановна, т. 318, к. 307 | R88: по наличию явления; 2 рассылки
A89: 0606047 | B89: другое ПО | C89: ПВ | D89: Форма № 3П-наука | E89: 2 квартал 2025 | F89: =VLOOKUP(I89,'Трансп. каталог'!$F$3:$I$743,2,0) -> не позднее 30.06.2025 | G89: =VLOOKUP(I89,'Трансп. каталог'!$F$3:$I$743,3,0) -> 0 | H89: 04022025 | I89: =CONCATENATE(A89,H89) -> 060604704022025 | J89: 10.07.2025 | K89: 30.06.2025 | L89: 24.07.2025 | M89: 30.06.2025 | N89: 07.07.2025 | O89: 09.07.2025 | Q89: Фаттахова Гульшат Гадынановна, т. 318, к. 307 | R89: по наличию явления; 2 рассылки
A90: 0606047 | B90: другое ПО | C90: ПВ | D90: Форма № 3П-наука | E90: 3 квартал 2025 | F90: =VLOOKUP(I90,'Трансп. каталог'!$F$3:$I$743,2,0) -> не позднее 29.09.2025 | G90: =VLOOKUP(I90,'Трансп. каталог'!$F$3:$I$743,3,0) -> 0 | H90: 04032025 | I90: =CONCATENATE(A90,H90) -> 060604704032025 | J90: 10.10.2025 | K90: 29.09.2025 | L90: 24.10.2025 | M90: 29.09.2025 | N90: 07.10.2025 | O90: 09.10.2025 | Q90: Фаттахова Гульшат Гадынановна, т. 318, к. 307 | R90: по наличию явления; 2 рассылки
A91: 0606047 | B91: другое ПО | C91: ПВ | D91: Форма № 3П-наука | E91: 4 квартал 2025 | F91: =VLOOKUP(I91,'Трансп. каталог'!$F$3:$I$743,2,0) -> не позднее 29.12.2025 | G91: =VLOOKUP(I91,'Трансп. каталог'!$F$3:$I$743,3,0) -> 0 | H91: 04042025 | I91: =CONCATENATE(A91,H91) -> 060604704042025 | J91: 12.01.2026 | K91: 29.12.2025 | L91: 30.01.2026 | M91: 29.12.2025 | N91: 09.01.2026 | O91: 11.01.2026 | Q91: Фаттахова Гульшат Гадынановна, т. 318, к. 307 | R91: по наличию явления; 2 рассылки
... A99: 0606049 | B99: другое ПО | C99: ПВ | D99: Форма № 3П-соц | E99: 4 квартал 2025 | F99: =VLOOKUP(I99,'Трансп. каталог'!$F$3:$I$743,2,0) -> не позднее 29.12.2025 | G99: =VLOOKUP(I99,'Трансп. каталог'!$F$3:$I$743,3,0) -> 0 | H99: 04042025 | I99: =CONCATENATE(A99,H99) -> 060604904042025 | J99: 12.01.2026 | K99: 29.12.2025 | L99: 30.01.2026 | M99: 29.12.2025 | N99: 09.01.2026 | O99: 11.01.2026 | Q99: Фаттахова Гульшат Гадынановна, т. 318, к. 307 | R99: по наличию явления; 2 рассылки
A100: 0606065 | B100: Ц | C100: ПВ | D100: № 1-Т(МС) | E100: 2024 | F100: =VLOOKUP(I100,'Трансп. каталог'!$F$3:$I$743,2,0) -> #N/A | G100: =VLOOKUP(I100,'Трансп. каталог'!$F$3:$I$743,3,0) -> #N/A | H100: 01012024 | I100: =CONCATENATE(A100,H100) -> 060606501012024 | J100: 01.03.2025 | K100: 05.02.2025 | L100: 14.04.2025 | M100: 05.02.2025 | N100: 26.02.2025 | O100: 28.02.2025 | P100: Смагина Татьяна Игоревна, т. 3-40, к. 301
A101: 0606066 | B101: Ц | C101: ПВ | D101: № 1-Т(ГС) | E101: 2024 | F101: =VLOOKUP(I101,'Трансп. каталог'!$F$3:$I$743,2,0) -> #N/A | G101: =VLOOKUP(I101,'Трансп. каталог'!$F$3:$I$743,3,0) -> #N/A | H101: 01012024 | I101: =CONCATENATE(A101,H101) -> 060606601012024 | J101: 01.03.2025 | K101: 05.02.2025 | L101: 14.04.2025 | M101: 05.02.2025 | N101: 26.02.2025 | O101: 28.02.2025 | P101: Смагина Татьяна Игоревна, т. 3-40, к. 301
A102: 0607002 | B102: Ц | C102: К | D102: 1-конъюнктура (опт) | E102: 1 квартал 2025 | F102: =VLOOKUP(I102,'Трансп. каталог'!$F$3:$I$743,2,0) -> не позднее 07.02.2025 | G102: =VLOOKUP(I102,'Трансп. каталог'!$F$3:$I$743,3,0) -> 0 | H102: 04012025 | I102: =CONCATENATE(A102,H102) -> 060700204012025 | J102: 10.03.2025 | K102: 03.03.2025 | L102: 18.03.2025 | M102: 03.03.2025 | N102: 05.03.2025 | O102: 07.03.2025 | P102: Камалова Наталья Вячеславовна, т. 622, к. 300 | Q102: Рублёва Наталья Адольфовна, т. 322, к. 307 | R102: =VLOOKUP(I102,'Трансп. каталог'!$F$3:$I$743,4,0) -> 0
A103: 0607002 | B103: Ц | C103: К | D103: 1-конъюнктура (опт) | E103: 2 квартал 2025 | F103: =VLOOKUP(I103,'Трансп. каталог'!$F$3:$I$743,2,0) -> не позднее 07.05.2025 | G103: =VLOOKUP(I103,'Трансп. каталог'!$F$3:$I$743,3,0) -> 0 | H103: 04022025 | I103: =CONCATENATE(A103,H103) -> 060700204022025 | J103: 10.06.2025 | K103: 02.06.2025 | L103: 19.06.2025 | M103: 02.06.2025 | N103: 05.06.2025 | O103: 06.06.2025 | P103: Камалова Наталья Вячеславовна, т. 622, к. 300 | Q103: Рублёва Наталья Адольфовна, т. 322, к. 307 | R103: =VLOOKUP(I103,'Трансп. каталог'!$F$3:$I$743,4,0) -> 0
A104: 0607002 | B104: Ц | C104: К | D104: 1-конъюнктура (опт) | E104: 3 квартал 2025 | F104: =VLOOKUP(I104,'Трансп. каталог'!$F$3:$I$743,2,0) -> не позднее 08.08.2025 | G104: =VLOOKUP(I104,'Трансп. каталог'!$F$3:$I$743,3,0) -> 0 | H104: 04032025 | I104: =CONCATENATE(A104,H104) -> 060700204032025 | J104: 10.09.2025 | K104: 01.09.2025 | L104: 16.09.2025 | M104: 01.09.2025 | N104: 03.09.2025 | O104: 05.09.2025 | P104: Камалова Наталья Вячеславовна, т. 622, к. 300 | Q104: Рублёва Наталья Адольфовна, т. 322, к. 307 | R104: =VLOOKUP(I104,'Трансп. каталог'!$F$3:$I$743,4,0) -> 0
A105: 0607002 | B105: Ц | C105: К | D105: 1-конъюнктура (опт) | E105: 4 квартал 2025 | F105: =VLOOKUP(I105,'Трансп. каталог'!$F$3:$I$743,2,0) -> не позднее 07.11.2025 | G105: =VLOOKUP(I105,'Трансп. каталог'!$F$3:$I$743,3,0) -> 0 | H105: 04042025 | I105: =CONCATENATE(A105,H105) -> 060700204042025 | J105: 10.12.2025 | K105: 01.12.2025 | L105: 16.12.2025 | M105: 01.12.2025 | N105: 03.12.2025 | O105: 05.12.2025 | P105: Камалова Наталья Вячеславовна, т. 622, к. 300 | Q105: Рублёва Наталья Адольфовна, т. 322, к. 307 | R105: =VLOOKUP(I105,'Трансп. каталог'!$F$3:$I$743,4,0) -> 0
A106: 0607017 | B106: Ц | C106: К | D106: №1-вывоз | E106: 1 квартал 2025 | F106: =VLOOKUP(I106,'Трансп. каталог'!$F$3:$I$743,2,0) -> не позднее 28.03.2025 | G106: =VLOOKUP(I106,'Трансп. каталог'!$F$3:$I$743,3,0) -> 0 | H106: 04012025 | I106: =CONCATENATE(A106,H106) -> 060701704012025 | J106: 14.04.2025 | K106: 04.04.2025 | L106: 22.05.2025 | M106: 04.04.2025 | N106: 09.04.2025 | O106: 11.04.2025 | P106: Осинцева Светлана Александровна, т. 2-24, к. 300 | Q106: Рублёва Наталья Адольфовна, т. 322, к. 307 | R106: =VLOOKUP(I106,'Трансп. каталог'!$F$3:$I$743,4,0) -> 0
A107: 0607017 | B107: Ц | C107: К | D107: №1-вывоз | E107: 2 квартал 2025 | F107: =VLOOKUP(I107,'Трансп. каталог'!$F$3:$I$743,2,0) -> не позднее 27.06.2025 | G107: =VLOOKUP(I107,'Трансп. каталог'!$F$3:$I$743,3,0) -> 0 | H107: 04022025 | I107: =CONCATENATE(A107,H107) -> 060701704022025 | J107: 14.07.2025 | K107: 04.07.2025 | L107: 15.08.2025 | M107: 04.07.2025 | N107: 09.07.2025 | O107: 11.07.2025 | P107: Осинцева Светлана Александровна, т. 2-24, к. 300 | Q107: Рублёва Наталья Адольфовна, т. 322, к. 307 | R107: =VLOOKUP(I107,'Трансп. каталог'!$F$3:$I$743,4,0) -> 0
...

Sheet Лист1

Sheet Трансп. каталог
I1: 45616
A2: ОКУД | B2: Индекс формы | C2: Наименование формы | D2: Отчётный период | E2: код отчётного периода | F2: ОКУД+Код (формула) | G2: Дата получения каталога со статусом "Итоговый" в АС ГС ОФСН | H2: Дата перевода каталога в "Архивный" статус | I2: Примечание
A3: 0606007 | B3: 57-Т | C3: Сведения о заработной плате работников по профессиям и должностям | D3: годовые | E3: 01012025 | F3: =CONCATENATE(A3,E3) -> 060600701012025 | G3: 24.10.2025 | H3: с 1 ноября по 30 ноября после отчетного периода
A4: 0606038 | B4: 1 | C4: Сведения о распределении численности работников по размерам начисленной заработной платы | D4: годовые | E4: 01012025 | F4: =CONCATENATE(A4,E4) -> 060603801012025 | G4: не позднее 21.04.2025 | H4: с 1-го рабочего дня по 20 мая после отчетного периода
A5: 0601009 | B5: 1-предприятие | C5: Основные сведения о деятельности организации | D5: годовые | E5: 01012024 | F5: =CONCATENATE(A5,E5) -> 060100901012024 | G5: 28.12.2024 | H5: С 1 марта по 15 апреля 2025 года
A6: 0601022 | B6: 1-МО | C6: Сведения об объектах инфраструктуры муниципального образования | D6: годовые | E6: 01012024 | F6: =CONCATENATE(A6,E6) -> 060102201012024 | G6: не позднее 28.12.2024 | H6: с 20 апреля по 1 июня после отчетного периода
A7: 0601023 | B7: Приложение к форме N 1-МО | C7: Показатели для оценки эффективности деятельности органов местного самоуправления муниципальных, городских округов и муниципальных районов | D7: годовые | E7: 01012024 | F7: =CONCATENATE(A7,E7) -> 060102301012024 | G7: не позднее 28.12.2024 | H7: с 1 апреля по 25 апреля после отчетного периода
A8: 0601024 | B8: МП (микро) - натура | C8: Сведения о производстве продукции микропредприятием | D8: годовые | E8: 01012024 | F8: =CONCATENATE(A8,E8) -> 060102401012024 | G8: не позднее 28.12.2024 | H8: с 1-го официального рабочего дня января по 25 января
A9: 0602001 | B9: 11 | C9: Сведения о наличии и движении основных фондов (средств) и других нефинансовых активов | D9: годовые | E9: 01012025 | F9: =CONCATENATE(A9,E9) -> 060200101012025 | G9: не позднее 13.02.2025 | H9: с 15-го февраля по 1-е апреля после отчетного периода
A10: 0602002 | B10: 11 (краткая) | C10: Сведения о наличии и движении основных фондов (средств) некоммерческих организаций | D10: годовые | E10: 01012025 | F10: =CONCATENATE(A10,E10) -> 060200201012025 | G10: не позднее 13.02.2025 | H10: с 15-го февраля по 1-е апреля после отчетного периода
A11: 0602003 | B11: 11 (сделка) | C11: Сведения о сделках с основными фондами на вторичном рынке и сдаче их в аренду | D11: годовые | E11: 01012025 | F11: =CONCATENATE(A11,E11) -> 060200301012025 | G11: не позднее 23.05.2025 | H11: с 25-го мая по 1-е июля после отчетного периода
A12: 0602004 | B12: 11-НА | C12: Сведения о наличии, движении и составе обращающихся контрактов, договоров аренды, лицензий, маркетинговых активов и гудвилла (деловой репутации организации | D12: годовые | E12: 01012025 | F12: =CONCATENATE(A12,E12) -> 060200401012025 | G12: не позднее 23.05.2025 | H12: с 25-го мая по 30-е июня после отчетного периода
A13: 0603026 | B13: 1-соцвыплаты | C13: Сведения об объемах социальных выплат населению по муниципальным районам (городским округам) | D13: годовые | E13: 01012024 | F13: =CONCATENATE(A13,E13) -> 060302601012024 | G13: не позднее 28.12.2024 | H13: 1 сентября
A14: 0603027 | B14: 3-соцподдержка | C14: Сведения о реализации мер социальной поддержки отдельных категорий граждан за счет средств консолидированного бюджета субъекта Российской Федерации | D14: годовые | E14: 01012024 | F14: =CONCATENATE(A14,E14) -> 060302701012024 | G14: не позднее 13.12.2024 | H14: с 1-го рабочего дня января по 10 февраля после отчетного периода
A15: 0604011 | B15: 2-наука | C15: Сведения о выполнении научных исследований и разработок | D15: годовые | E15: 01012025 | F15: =CONCATENATE(A15,E15) -> 060401101012025 | G15: не позднее 14.02.2025 | H15: со 2 по 11 апреля после отчетного периода
A16: 0604016 | B16: 1-технология | C16: Сведения о разработке и (или) использовании передовых производственных технологий | D16: годовые | E16: 01012024 | F16: =CONCATENATE(A16,E16) -> 060401601012024 | G16: не позднее 27.12.2024 | H16: с 13 января по 31 января после отчетного периода
A17: 0604017 | B17: 4-инновация | C17: Сведения об инновационной деятельности организации | D17: годовые | E17: 01012025 | F17: =CONCATENATE(A17,E17) -> 060401701012025 | G17: не позднее 19.02.2025 | H17: со 2 по 15 апреля
A18: 0604018 | B18: 3-информ | C18: Сведения об использовании цифровых технологий и производстве связанных с ними товаров и услуг | D18: годовые | E18: 01012025 | F18: =CONCATENATE(A18,E18) -> 060401801012025 | G18: не позднее 13.02.2025 | H18: с 15 марта по 1 апреля после отчетного периода
A19: 0604030 | B19: 1-НК | C19: Сведения об организации, осуществляющей образовательную деятельность по программам подготовки научно-педагогических кадров в аспирантуре, программам ординатуры, программам ассистентуры-стажировки, а также осуществляющей подготовку научных кадров в до | D19: годовые | E19: 01012024 | F19: =CONCATENATE(A19,E19) -> 060403001012024 | G19: не позднее 24.12.2024 | H19: C 9 по 19 января после отчетного периода
A20: 0605101 | B20: 1-АЭ | C20: Сведения об административных правонарушениях в сфере экономики | D20: годовые | E20: 01012024 | F20: =CONCATENATE(A20,E20) -> 060510101012024 | G20: не позднее 28.12.2024 | H20: с 15 февраля по 15 марта после отчетного периода
A21: 0606002 | B21: 1-Т | C21: Сведения о численности и заработной плате работников | D21: годовые | E21: 01012024 | F21: =CONCATENATE(A21,E21) -> 060600201012024 | G21: не позднее 28.12.2024 | H21: с 1-го рабочего дня по 31 января после отчетного периода
... A98: 0601011 | B98: 2-МП инновация | C98: Сведения об инновационной деятельности малого предприятия | D98: годовые | E98: 01012025 | F98: =CONCATENATE(A98,E98) -> 060101101012025 | G98: не позднее 06.03.2025 | H98: с 9 по 15 апреля после отчетного периода
A99: 0614046 | B99: 3-рынок | C99: Сведения о числе торговых мест на рынках | D99: 1 квартал 2025 г. | E99: 04012025 | F99: =CONCATENATE(A99,E99) -> 061404604012025 | G99: не позднее 28.03.2025
A100: 0614046 | B100: 3-рынок | C100: Сведения о числе торговых мест на рынках | D100: 2 квартал 2025 г. | E100: 04022025 | F100: =CONCATENATE(A100,E100) -> 061404604022025 | G100: не позднее 27.06.2025
A101: 0614046 | B101: 3-рынок | C101: Сведения о числе торговых мест на рынках | D101: 1 полугодие 2025 г. | E101: 02012025 | F101: =CONCATENATE(A101,E101) -> 061404602012025 | G101: не позднее 27.06.2025
A102: 0614046 | B102: 3-рынок | C102: Сведения о числе торговых мест на рынках | D102: 3 квартал 2025 г. | E102: 04032025 | F102: =CONCATENATE(A102,E102) -> 061404604032025 | G102: не позднее 26.09.2025
A103: 0614046 | B103: 3-рынок | C103: Сведения о числе торговых мест на рынках | D103: 4 квартал 2025 г. | E103: 04042025 | F103: =CONCATENATE(A103,E103) -> 061404604042025 | G103: не позднее 30.12.2025
A104: 0614046 | B104: 3-рынок | C104: Сведения о числе торговых мест на рынках | D104: 2 полугодие 2025 г. | E104: 02022025 | F104: =CONCATENATE(A104,E104) -> 061404602022025 | G104: не позднее 30.12.2025
A105: 0614001 | B105: 1-конъюнктура | C105: Обследование конъюнктуры и деловой активности в розничной торговле | D105: 1 квартал 2025 г. | E105: 04012025 | F105: =CONCATENATE(A105,E105) -> 061400104012025 | G105: не позднее 29.01.2025
A106: 0614001 | B106: 1-конъюнктура | C106: Обследование конъюнктуры и деловой активности в розничной торговле | D106: 2 квартал 2025 г. | E106: 04022025 | F106: =CONCATENATE(A106,E106) -> 061400104022025 | G106: не позднее 29.04.2025
A107: 0614001 | B107: 1-конъюнктура | C107: Обследование конъюнктуры и деловой активности в розничной торговле | D107: 1 полугодие 2025 г. | E107: 02012025 | F107: =CONCATENATE(A107,E107) -> 061400102012025 | G107: не позднее 29.04.2025
A108: 0614001 | B108: 1-конъюнктура | C108: Обследование конъюнктуры и деловой активности в розничной торговле | D108: 3 квартал 2025 г. | E108: 04032025 | F108: =CONCATENATE(A108,E108) -> 061400104032025 | G108: не позднее 29.07.2025
A109: 0614001 | B109: 1-конъюнктура | C109: Обследование конъюнктуры и деловой активности в розничной торговле | D109: 4 квартал 2025 г. | E109: 04042025 | F109: =CONCATENATE(A109,E109) -> 061400104042025 | G109: не позднее 29.10.2025
A110: 0614001 | B110: 1-конъюнктура | C110: Обследование конъюнктуры и деловой активности в розничной торговле | D110: 2 полугодие 2025 г. | E110: 02022025 | F110: =CONCATENATE(A110,E110) -> 061400102022025 | G110: не позднее 29.10.2025
... A509: 0610013 | B509: П-1 | C509: Сведения о производстве и отгрузке товаров и услуг | D509: февраль 2025 г. | E509: 12022025 | F509: =CONCATENATE(A509,E509) -> 061001312022025 | G509: 27.02.2025
A510: 0610013 | B510: П-1 | C510: Сведения о производстве и отгрузке товаров и услуг | D510: март 2025 г. | E510: 12032025 | F510: =CONCATENATE(A510,E510) -> 061001312032025 | G510: 45744
A511: 0610013 | B511: П-1 | C511: Сведения о производстве и отгрузке товаров и услуг | D511: апрель 2025 г. | E511: 12042025 | F511: =CONCATENATE(A511,E511) -> 061001312042025 | G511: 29.04.2025
A512: 0610013 | B512: П-1 | C512: Сведения о производстве и отгрузке товаров и услуг | D512: май 2025 г. | E512: 12052025 | F512: =CONCATENATE(A512,E512) -> 061001312052025 | G512: 29.05.2025
A513: 0610013 | B513: П-1 | C513: Сведения о производстве и отгрузке товаров и услуг | D513: июнь 2025 г. | E513: 12062025 | F513: =CONCATENATE(A513,E513) -> 061001312062025 | G513: 27.06.2025
A514: 0610013 | B514: П-1 | C514: Сведения о производстве и отгрузке товаров и услуг | D514: июль 2025 г. | E514: 12072025 | F514: =CONCATENATE(A514,E514) -> 061001312072025 | G514: 30.07.2025
A515: 0610013 | B515: П-1 | C515: Сведения о производстве и отгрузке товаров и услуг | D515: август 2025 г. | E515: 12082025 | F515: =CONCATENATE(A515,E515) -> 061001312082025 | G515: 45897
A516: 0610013 | B516: П-1 | C516: Сведения о производстве и отгрузке товаров и услуг | D516: сентябрь 2025 г. | E516: 12092025 | F516: =CONCATENATE(A516,E516) -> 061001312092025 | G516: 29.09.2025
A517: 0610013 | B517: П-1 | C517: Сведения о производстве и отгрузке товаров и услуг | D517: октябрь 2025 г. | E517: 12102025 | F517: =CONCATENATE(A517,E517) -> 061001312102025 | G517: 30.10.2025
A518: 0610013 | B518: П-1 | C518: Сведения о производстве и отгрузке товаров и услуг | D518: ноябрь 2025 г. | E518: 12112025 | F518: =CONCATENATE(A518,E518) -> 061001312112025 | G518: 27.11.2025
A519: 0610013 | B519: П-1 | C519: Сведения о производстве и отгрузке товаров и услуг | D519: декабрь 2025 г. | E519: 12122025 | F519: =CONCATENATE(A519,E519) -> 061001312122025 | G519: 29.12.2025
A520: 0612010 | B520: 1-разрешение | C520: Сведения о выданных разрешениях на строительство и разрешениях на ввод объектов в эксплуатацию | D520: январь 2025 г. | E520: 12012025 | F520: =CONCATENATE(A520,E520) -> 061201012012025 | G520: не позднее 29.01.2025
A521: 0612010 | B521: 1-разрешение | C521: Сведения о выданных разрешениях на строительство и разрешениях на ввод объектов в эксплуатацию | D521: февраль 2025 г. | E521: 12022025 | F521: =CONCATENATE(A521,E521) -> 061201012022025 | G521: не позднее 27.02.2025
A522: 0612010 | B522: 1-разрешение | C522: Сведения о выданных разрешениях на строительство и разрешениях на ввод объектов в эксплуатацию | D522: март 2025 г. | E522: 12032025 | F522: =CONCATENATE(A522,E522) -> 061201012032025 | G522: не позднее 28.03.2025
A523: 0612010 | B523: 1-разрешение | C523: Сведения о выданных разрешениях на строительство и разрешениях на ввод объектов в эксплуатацию | D523: апрель 2025 г. | E523: 12042025 | F523: =CONCATENATE(A523,E523) -> 061201012042025 | G523: не позднее 29.04.2025
A524: 0612010 | B524: 1-разрешение | C524: Сведения о выданных разрешениях на строительство и разрешениях на ввод объектов в эксплуатацию | D524: май 2025 г. | E524: 12052025 | F524: =CONCATENATE(A524,E524) -> 061201012052025 | G524: не позднее 29.05.2025
A525: 0612010 | B525: 1-разрешение | C525: Сведения о выданных разрешениях на строительство и разрешениях на ввод объектов в эксплуатацию | D525: июнь 2025 г. | E525: 12062025 | F525: =CONCATENATE(A525,E525) -> 061201012062025 | G525: не позднее 27.06.2025
A526: 0612010 | B526: 1-разрешение | C526: Сведения о выданных разрешениях на строительство и разрешениях на ввод объектов в эксплуатацию | D526: июль 2025 г. | E526: 12072025 | F526: =CONCATENATE(A526,E526) -> 061201012072025 | G526: не позднее 30.07.2025
A527: 0612010 | B527: 1-разрешение | C527: Сведения о выданных разрешениях на строительство и разрешениях на ввод объектов в эксплуатацию | D527: август 2025 г. | E527: 12082025 | F527: =CONCATENATE(A527,E527) -> 061201012082025 | G527: не позднее 28.08.2025
... A743: 0610067 | B743: 1-автобензин | C743: Сведения о производстве нефтепродуктов | D743: 29.12.2025 - 31.12.2025 | E743: 53532025 | F743: =CONCATENATE(A743,E743) -> 061006753532025 | G743: Последний рабочий день недели
